{
  "branch": "main",
  "failed_at_utc": "2026-07-24T17:39:14.292489+00:00",
  "log_tail": "  Using cached pygments-2.20.0-py3-none-any.whl.metadata (2.5 kB)\nCollecting markdown-it-py>=2.2.0 (from rich->bandit>=1.8->tsao-scicomputation==3.0.1)\n  Using cached markdown_it_py-4.2.0-py3-none-any.whl.metadata (7.4 kB)\nCollecting mdurl~=0.1 (from markdown-it-py>=2.2.0->rich->bandit>=1.8->tsao-scicomputation==3.0.1)\n  Using cached mdurl-0.1.2-py3-none-any.whl.metadata (1.6 kB)\nUsing cached bandit-1.9.4-py3-none-any.whl (134 kB)\nUsing cached build-1.5.0-py3-none-any.whl (26 kB)\nUsing cached coverage-7.15.2-cp313-cp313-manylinux1_x86_64.manylinux_2_28_x86_64.manylinux_2_5_x86_64.whl (255 kB)\nUsing cached jsonschema-4.26.0-py3-none-any.whl (90 kB)\nUsing cached attrs-26.1.0-py3-none-any.whl (67 kB)\nUsing cached jsonschema_specifications-2025.9.1-py3-none-any.whl (18 kB)\nUsing cached mypy-2.3.0-cp313-cp313-manylinux2014_x86_64.manylinux_2_17_x86_64.manylinux_2_28_x86_64.whl (15.2 MB)\nUsing cached ast_serialize-0.6.0-cp39-abi3-manylinux_2_17_x86_64.manylinux2014_x86_64.whl (1.3 MB)\nUsing cached librt-0.13.0-cp313-cp313-manylinux2014_x86_64.manylinux_2_17_x86_64.manylinux_2_28_x86_64.whl (531 kB)\nUsing cached mypy_extensions-1.1.0-py3-none-any.whl (5.0 kB)\nUsing cached packaging-26.2-py3-none-any.whl (100 kB)\nUsing cached pathspec-1.1.1-py3-none-any.whl (57 kB)\nUsing cached pytest-9.1.1-py3-none-any.whl (386 kB)\nUsing cached pluggy-1.6.0-py3-none-any.whl (20 kB)\nUsing cached iniconfig-2.3.0-py3-none-any.whl (7.5 kB)\nUsing cached pygments-2.20.0-py3-none-any.whl (1.2 MB)\nUsing cached pyyaml-6.0.3-cp313-cp313-manylinux2014_x86_64.manylinux_2_17_x86_64.manylinux_2_28_x86_64.whl (801 kB)\nUsing cached referencing-0.37.0-py3-none-any.whl (26 kB)\nUsing cached rpds_py-2026.6.3-cp313-cp313-manylinux_2_17_x86_64.manylinux2014_x86_64.whl (365 kB)\nUsing cached ruff-0.16.0-py3-none-manylinux_2_17_x86_64.manylinux2014_x86_64.whl (11.4 MB)\nUsing cached setuptools-83.0.0-py3-none-any.whl (1.0 MB)\nUsing cached stevedore-5.9.0-py3-none-any.whl (54 kB)\nUsing cached types_jsonschema-4.26.0.20260518-py3-none-any.whl (16 kB)\nUsing cached typing_extensions-4.16.0-py3-none-any.whl (45 kB)\nUsing cached wheel-0.47.0-py3-none-any.whl (32 kB)\nUsing cached pyproject_hooks-1.2.0-py3-none-any.whl (10 kB)\nUsing cached rich-15.0.0-py3-none-any.whl (310 kB)\nUsing cached markdown_it_py-4.2.0-py3-none-any.whl (91 kB)\nUsing cached mdurl-0.1.2-py3-none-any.whl (10.0 kB)\nBuilding wheels for collected packages: tsao-scicomputation\n  Building editable for tsao-scicomputation (pyproject.toml): started\n  Building editable for tsao-scicomputation (pyproject.toml): finished with status 'done'\n  Created wheel for tsao-scicomputation: filename=tsao_scicomputation-3.0.1-0.editable-py3-none-any.whl size=7050 sha256=d2e84bc2bc5955a6fb91f636d88f72e2a580a03cbae77ab73d20e6272ad0ca14\n  Stored in directory: /tmp/pip-ephem-wheel-cache-mxkvj30n/wheels/0b/5e/4c/c753a318e94b62c7a2dea3c242cc346ea1bcbad20760c46702\nSuccessfully built tsao-scicomputation\nInstalling collected packages: typing_extensions, tsao-scicomputation, stevedore, setuptools, ruff, rpds-py, PyYAML, pyproject_hooks, pygments, pluggy, pathspec, packaging, mypy_extensions, mdurl, librt, iniconfig, coverage, attrs, ast-serialize, wheel, referencing, pytest, mypy, markdown-it-py, build, types-jsonschema, rich, jsonschema-specifications, jsonschema, bandit\n\nSuccessfully installed PyYAML-6.0.3 ast-serialize-0.6.0 attrs-26.1.0 bandit-1.9.4 build-1.5.0 coverage-7.15.2 iniconfig-2.3.0 jsonschema-4.26.0 jsonschema-specifications-2025.9.1 librt-0.13.0 markdown-it-py-4.2.0 mdurl-0.1.2 mypy-2.3.0 mypy_extensions-1.1.0 packaging-26.2 pathspec-1.1.1 pluggy-1.6.0 pygments-2.20.0 pyproject_hooks-1.2.0 pytest-9.1.1 referencing-0.37.0 rich-15.0.0 rpds-py-2026.6.3 ruff-0.16.0 setuptools-83.0.0 stevedore-5.9.0 tsao-scicomputation-3.0.1 types-jsonschema-4.26.0.20260518 typing_extensions-4.16.0 wheel-0.47.0\n/home/runner/work/TsaoSciComputation/TsaoSciComputation/scripts/_apply_v302_governance.py:424: SyntaxWarning: invalid escape sequence '\\s'\n  pattern = re.compile(r\"uses:\\s+[^@\\s]+@([0-9a-f]{40})$\")\n{\"confidence_model\": \"C0-C5\", \"tests_added\": 8}\n{\"release_date\": \"2026-07-24\", \"version\": \"3.0.2\"}\nObtaining file:///home/runner/work/TsaoSciComputation/TsaoSciComputation\n  Installing build dependencies: started\n  Installing build dependencies: finished with status 'done'\n  Checking if build backend supports build_editable: started\n  Checking if build backend supports build_editable: finished with status 'done'\n  Getting requirements to build editable: started\n  Getting requirements to build editable: finished with status 'done'\n  Preparing editable metadata (pyproject.toml): started\n  Preparing editable metadata (pyproject.toml): finished with status 'done'\nRequirement already satisfied: pytest>=8 in /opt/hostedtoolcache/Python/3.13.14/x64/lib/python3.13/site-packages (from tsao-scicomputation==3.0.2) (9.1.1)\nRequirement already satisfied: coverage>=7 in /opt/hostedtoolcache/Python/3.13.14/x64/lib/python3.13/site-packages (from tsao-scicomputation==3.0.2) (7.15.2)\nRequirement already satisfied: jsonschema>=4 in /opt/hostedtoolcache/Python/3.13.14/x64/lib/python3.13/site-packages (from tsao-scicomputation==3.0.2) (4.26.0)\nRequirement already satisfied: PyYAML>=6 in /opt/hostedtoolcache/Python/3.13.14/x64/lib/python3.13/site-packages (from tsao-scicomputation==3.0.2) (6.0.3)\nRequirement already satisfied: ruff>=0.12 in /opt/hostedtoolcache/Python/3.13.14/x64/lib/python3.13/site-packages (from tsao-scicomputation==3.0.2) (0.16.0)\nRequirement already satisfied: mypy>=1.16 in /opt/hostedtoolcache/Python/3.13.14/x64/lib/python3.13/site-packages (from tsao-scicomputation==3.0.2) (2.3.0)\nRequirement already satisfied: bandit>=1.8 in /opt/hostedtoolcache/Python/3.13.14/x64/lib/python3.13/site-packages (from tsao-scicomputation==3.0.2) (1.9.4)\nRequirement already satisfied: build>=1.2 in /opt/hostedtoolcache/Python/3.13.14/x64/lib/python3.13/site-packages (from tsao-scicomputation==3.0.2) (1.5.0)\nRequirement already satisfied: types-jsonschema>=4.25 in /opt/hostedtoolcache/Python/3.13.14/x64/lib/python3.13/site-packages (from tsao-scicomputation==3.0.2) (4.26.0.20260518)\nRequirement already satisfied: setuptools>=80 in /opt/hostedtoolcache/Python/3.13.14/x64/lib/python3.13/site-packages (from tsao-scicomputation==3.0.2) (83.0.0)\nRequirement already satisfied: wheel>=0.45 in /opt/hostedtoolcache/Python/3.13.14/x64/lib/python3.13/site-packages (from tsao-scicomputation==3.0.2) (0.47.0)\nCollecting pip-audit==2.10.0 (from tsao-scicomputation==3.0.2)\n  Downloading pip_audit-2.10.0-py3-none-any.whl.metadata (28 kB)\nCollecting CacheControl>=0.13.0 (from CacheControl[filecache]>=0.13.0->pip-audit==2.10.0->tsao-scicomputation==3.0.2)\n  Downloading cachecontrol-0.14.4-py3-none-any.whl.metadata (3.1 kB)\nCollecting cyclonedx-python-lib<12,>=5 (from pip-audit==2.10.0->tsao-scicomputation==3.0.2)\n  Downloading cyclonedx_python_lib-11.11.0-py3-none-any.whl.metadata (6.9 kB)\nRequirement already satisfied: packaging>=23.0.0 in /opt/hostedtoolcache/Python/3.13.14/x64/lib/python3.13/site-packages (from pip-audit==2.10.0->tsao-scicomputation==3.0.2) (26.2)\nCollecting pip-api>=0.0.28 (from pip-audit==2.10.0->tsao-scicomputation==3.0.2)\n  Downloading pip_api-0.0.34-py3-none-any.whl.metadata (6.6 kB)\nCollecting pip-requirements-parser>=32.0.0 (from pip-audit==2.10.0->tsao-scicomputation==3.0.2)\n  Downloading pip_requirements_parser-32.0.1-py3-none-any.whl.metadata (9.3 kB)\nCollecting requests>=2.31.0 (from pip-audit==2.10.0->tsao-scicomputation==3.0.2)\n  Downloading requests-2.34.2-py3-none-any.whl.metadata (4.8 kB)\nRequirement already satisfied: rich>=12.4 in /opt/hostedtoolcache/Python/3.13.14/x64/lib/python3.13/site-packages (from pip-audit==2.10.0->tsao-scicomputation==3.0.2) (15.0.0)\nCollecting tomli>=2.2.1 (from pip-audit==2.10.0->tsao-scicomputation==3.0.2)\n  Downloading tomli-2.4.1-cp313-cp313-manylinux2014_x86_64.manylinux_2_17_x86_64.manylinux_2_28_x86_64.whl.metadata (10 kB)\nCollecting tomli-w>=1.2.0 (from pip-audit==2.10.0->tsao-scicomputation==3.0.2)\n  Downloading tomli_w-1.2.0-py3-none-any.whl.metadata (5.7 kB)\nCollecting platformdirs>=4.2.0 (from pip-audit==2.10.0->tsao-scicomputation==3.0.2)\n  Downloading platformdirs-4.11.0-py3-none-any.whl.metadata (5.5 kB)\nCollecting license-expression<31,>=30 (from cyclonedx-python-lib<12,>=5->pip-audit==2.10.0->tsao-scicomputation==3.0.2)\n  Downloading license_expression-30.4.4-py3-none-any.whl.metadata (11 kB)\nCollecting packageurl-python<2,>=0.11 (from cyclonedx-python-lib<12,>=5->pip-audit==2.10.0->tsao-scicomputation==3.0.2)\n  Downloading packageurl_python-0.17.6-py3-none-any.whl.metadata (5.1 kB)\nCollecting py-serializable<3.0.0,>=2.1.0 (from cyclonedx-python-lib<12,>=5->pip-audit==2.10.0->tsao-scicomputation==3.0.2)\n  Downloading py_serializable-2.1.0-py3-none-any.whl.metadata (4.3 kB)\nCollecting sortedcontainers<3.0.0,>=2.4.0 (from cyclonedx-python-lib<12,>=5->pip-audit==2.10.0->tsao-scicomputation==3.0.2)\n  Downloading sortedcontainers-2.4.0-py2.py3-none-any.whl.metadata (10 kB)\nCollecting boolean.py>=4.0 (from license-expression<31,>=30->cyclonedx-python-lib<12,>=5->pip-audit==2.10.0->tsao-scicomputation==3.0.2)\n  Downloading boolean_py-5.0-py3-none-any.whl.metadata (2.3 kB)\nCollecting defusedxml<0.8.0,>=0.7.1 (from py-serializable<3.0.0,>=2.1.0->cyclonedx-python-lib<12,>=5->pip-audit==2.10.0->tsao-scicomputation==3.0.2)\n  Downloading defusedxml-0.7.1-py2.py3-none-any.whl.metadata (32 kB)\nRequirement already satisfied: stevedore>=1.20.0 in /opt/hostedtoolcache/Python/3.13.14/x64/lib/python3.13/site-packages (from bandit>=1.8->tsao-scicomputation==3.0.2) (5.9.0)\nRequirement already satisfied: pyproject_hooks in /opt/hostedtoolcache/Python/3.13.14/x64/lib/python3.13/site-packages (from build>=1.2->tsao-scicomputation==3.0.2) (1.2.0)\nCollecting msgpack<2.0.0,>=0.5.2 (from CacheControl>=0.13.0->CacheControl[filecache]>=0.13.0->pip-audit==2.10.0->tsao-scicomputation==3.0.2)\n  Downloading msgpack-1.2.1-cp313-cp313-manylinux2014_x86_64.manylinux_2_17_x86_64.manylinux_2_28_x86_64.whl.metadata (8.3 kB)\nCollecting filelock>=3.8.0 (from CacheControl[filecache]>=0.13.0->pip-audit==2.10.0->tsao-scicomputation==3.0.2)\n  Downloading filelock-3.32.0-py3-none-any.whl.metadata (2.0 kB)\nRequirement already satisfied: attrs>=22.2.0 in /opt/hostedtoolcache/Python/3.13.14/x64/lib/python3.13/site-packages (from jsonschema>=4->tsao-scicomputation==3.0.2) (26.1.0)\nRequirement already satisfied: jsonschema-specifications>=2023.03.6 in /opt/hostedtoolcache/Python/3.13.14/x64/lib/python3.13/site-packages (from jsonschema>=4->tsao-scicomputation==3.0.2) (2025.9.1)\nRequirement already satisfied: referencing>=0.28.4 in /opt/hostedtoolcache/Python/3.13.14/x64/lib/python3.13/site-packages (from jsonschema>=4->tsao-scicomputation==3.0.2) (0.37.0)\nRequirement already satisfied: rpds-py>=0.25.0 in /opt/hostedtoolcache/Python/3.13.14/x64/lib/python3.13/site-packages (from jsonschema>=4->tsao-scicomputation==3.0.2) (2026.6.3)\nRequirement already satisfied: typing_extensions>=4.6.0 in /opt/hostedtoolcache/Python/3.13.14/x64/lib/python3.13/site-packages (from mypy>=1.16->tsao-scicomputation==3.0.2) (4.16.0)\nRequirement already satisfied: mypy_extensions>=1.0.0 in /opt/hostedtoolcache/Python/3.13.14/x64/lib/python3.13/site-packages (from mypy>=1.16->tsao-scicomputation==3.0.2) (1.1.0)\nRequirement already satisfied: pathspec>=1.0.0 in /opt/hostedtoolcache/Python/3.13.14/x64/lib/python3.13/site-packages (from mypy>=1.16->tsao-scicomputation==3.0.2) (1.1.1)\nRequirement already satisfied: librt>=0.13.0 in /opt/hostedtoolcache/Python/3.13.14/x64/lib/python3.13/site-packages (from mypy>=1.16->tsao-scicomputation==3.0.2) (0.13.0)\nRequirement already satisfied: ast-serialize<1.0.0,>=0.6.0 in /opt/hostedtoolcache/Python/3.13.14/x64/lib/python3.13/site-packages (from mypy>=1.16->tsao-scicomputation==3.0.2) (0.6.0)\nRequirement already satisfied: pip in /opt/hostedtoolcache/Python/3.13.14/x64/lib/python3.13/site-packages (from pip-api>=0.0.28->pip-audit==2.10.0->tsao-scicomputation==3.0.2) (26.1.2)\nCollecting pyparsing (from pip-requirements-parser>=32.0.0->pip-audit==2.10.0->tsao-scicomputation==3.0.2)\n  Downloading pyparsing-3.3.2-py3-none-any.whl.metadata (5.8 kB)\nRequirement already satisfied: iniconfig>=1.0.1 in /opt/hostedtoolcache/Python/3.13.14/x64/lib/python3.13/site-packages (from pytest>=8->tsao-scicomputation==3.0.2) (2.3.0)\nRequirement already satisfied: pluggy<2,>=1.5 in /opt/hostedtoolcache/Python/3.13.14/x64/lib/python3.13/site-packages (from pytest>=8->tsao-scicomputation==3.0.2) (1.6.0)\nRequirement already satisfied: pygments>=2.7.2 in /opt/hostedtoolcache/Python/3.13.14/x64/lib/python3.13/site-packages (from pytest>=8->tsao-scicomputation==3.0.2) (2.20.0)\nCollecting charset_normalizer<4,>=2 (from requests>=2.31.0->pip-audit==2.10.0->tsao-scicomputation==3.0.2)\n  Downloading charset_normalizer-3.4.9-cp313-cp313-manylinux2014_x86_64.manylinux_2_17_x86_64.manylinux_2_28_x86_64.whl.metadata (41 kB)\nCollecting idna<4,>=2.5 (from requests>=2.31.0->pip-audit==2.10.0->tsao-scicomputation==3.0.2)\n  Downloading idna-3.18-py3-none-any.whl.metadata (6.1 kB)\nCollecting urllib3<3,>=1.26 (from requests>=2.31.0->pip-audit==2.10.0->tsao-scicomputation==3.0.2)\n  Downloading urllib3-2.7.0-py3-none-any.whl.metadata (6.9 kB)\nCollecting certifi>=2023.5.7 (from requests>=2.31.0->pip-audit==2.10.0->tsao-scicomputation==3.0.2)\n  Downloading certifi-2026.7.22-py3-none-any.whl.metadata (2.5 kB)\nRequirement already satisfied: markdown-it-py>=2.2.0 in /opt/hostedtoolcache/Python/3.13.14/x64/lib/python3.13/site-packages (from rich>=12.4->pip-audit==2.10.0->tsao-scicomputation==3.0.2) (4.2.0)\nRequirement already satisfied: mdurl~=0.1 in /opt/hostedtoolcache/Python/3.13.14/x64/lib/python3.13/site-packages (from markdown-it-py>=2.2.0->rich>=12.4->pip-audit==2.10.0->tsao-scicomputation==3.0.2) (0.1.2)\nDownloading pip_audit-2.10.0-py3-none-any.whl (61 kB)\nDownloading cyclonedx_python_lib-11.11.0-py3-none-any.whl (528 kB)\n   \u2501\u2501\u2501\u2501\u2501\u2501\u2501\u2501\u2501\u2501\u2501\u2501\u2501\u2501\u2501\u2501\u2501\u2501\u2501\u2501\u2501\u2501\u2501\u2501\u2501\u2501\u2501\u2501\u2501\u2501\u2501\u2501\u2501\u2501\u2501\u2501\u2501\u2501\u2501\u2501 528.7/528.7 kB 22.8 MB/s  0:00:00\nDownloading license_expression-30.4.4-py3-none-any.whl (120 kB)\nDownloading packageurl_python-0.17.6-py3-none-any.whl (36 kB)\nDownloading py_serializable-2.1.0-py3-none-any.whl (23 kB)\nDownloading defusedxml-0.7.1-py2.py3-none-any.whl (25 kB)\nDownloading sortedcontainers-2.4.0-py2.py3-none-any.whl (29 kB)\nDownloading boolean_py-5.0-py3-none-any.whl (26 kB)\nDownloading cachecontrol-0.14.4-py3-none-any.whl (22 kB)\nDownloading msgpack-1.2.1-cp313-cp313-manylinux2014_x86_64.manylinux_2_17_x86_64.manylinux_2_28_x86_64.whl (416 kB)\nDownloading filelock-3.32.0-py3-none-any.whl (97 kB)\nDownloading pip_api-0.0.34-py3-none-any.whl (120 kB)\nDownloading pip_requirements_parser-32.0.1-py3-none-any.whl (35 kB)\nDownloading platformdirs-4.11.0-py3-none-any.whl (23 kB)\nDownloading requests-2.34.2-py3-none-any.whl (73 kB)\nDownloading charset_normalizer-3.4.9-cp313-cp313-manylinux2014_x86_64.manylinux_2_17_x86_64.manylinux_2_28_x86_64.whl (223 kB)\nDownloading idna-3.18-py3-none-any.whl (65 kB)\nDownloading urllib3-2.7.0-py3-none-any.whl (131 kB)\nDownloading certifi-2026.7.22-py3-none-any.whl (136 kB)\nDownloading tomli-2.4.1-cp313-cp313-manylinux2014_x86_64.manylinux_2_17_x86_64.manylinux_2_28_x86_64.whl (251 kB)\nDownloading tomli_w-1.2.0-py3-none-any.whl (6.7 kB)\nDownloading pyparsing-3.3.2-py3-none-any.whl (122 kB)\nBuilding wheels for collected packages: tsao-scicomputation\n  Building editable for tsao-scicomputation (pyproject.toml): started\n  Building editable for tsao-scicomputation (pyproject.toml): finished with status 'done'\n  Created wheel for tsao-scicomputation: filename=tsao_scicomputation-3.0.2-0.editable-py3-none-any.whl size=7258 sha256=dbad3d7fbde60f2a11fb60516dbd9c05516561de46ecf5ed846bf0b4e57bff7a\n  Stored in directory: /tmp/pip-ephem-wheel-cache-omco_fie/wheels/0b/5e/4c/c753a318e94b62c7a2dea3c242cc346ea1bcbad20760c46702\nSuccessfully built tsao-scicomputation\nInstalling collected packages: sortedcontainers, boolean.py, urllib3, tsao-scicomputation, tomli-w, tomli, pyparsing, platformdirs, pip-api, packageurl-python, msgpack, license-expression, idna, filelock, defusedxml, charset_normalizer, certifi, requests, py-serializable, pip-requirements-parser, cyclonedx-python-lib, CacheControl, pip-audit\n  Attempting uninstall: tsao-scicomputation\n    Found existing installation: tsao-scicomputation 3.0.1\n    Uninstalling tsao-scicomputation-3.0.1:\n      Successfully uninstalled tsao-scicomputation-3.0.1\n\nSuccessfully installed CacheControl-0.14.4 boolean.py-5.0 certifi-2026.7.22 charset_normalizer-3.4.9 cyclonedx-python-lib-11.11.0 defusedxml-0.7.1 filelock-3.32.0 idna-3.18 license-expression-30.4.4 msgpack-1.2.1 packageurl-python-0.17.6 pip-api-0.0.34 pip-audit-2.10.0 pip-requirements-parser-32.0.1 platformdirs-4.11.0 py-serializable-2.1.0 pyparsing-3.3.2 requests-2.34.2 sortedcontainers-2.4.0 tomli-2.4.1 tomli-w-1.2.0 tsao-scicomputation-3.0.2 urllib3-2.7.0\nF841 Local variable `init_path` is assigned to but never used\n   --> scripts/_apply_confidence_model.py:155:5\n    |\n153 |     )\n154 |\n155 |     init_path = ROOT / \"tsao_computation\" / \"validation\" / \"__init__.py\"\n    |     ^^^^^^^^^\n156 |     write(\n157 |         \"tsao_computation/validation/__init__.py\",\n    |\nhelp: Remove assignment to unused variable `init_path`\n\nFound 4 errors (3 fixed, 1 remaining).\nNo fixes available (1 hidden fix can be enabled with the `--unsafe-fixes` option).",
  "schema_version": "1.0",
  "stage": "format-and-generate",
  "status": "FAILED",
  "temporary_branch_created": false
}
